{
  "schema_version": 2,
  "description": "Unified Agroverse event registry. 'upcoming' = operational events (source: each go_to_market/events/<slug>/event.json). 'past' = published cacao-circle pages (source: agroverse_shop/event-details-registration, generated by its build_events_json.py). Regenerate with build_index.py. Convention: agentic_ai_context/EVENTS.md",
  "generated_at": "2026-06-04T00:00:00Z",
  "generated_by": "build_index.py",
  "upcoming": {
    "source": "go_to_market/events",
    "count": 3,
    "events": [
      {
        "schema_version": 1,
        "slug": "sftechfestjune26",
        "name": "SF Tech Fest 2026",
        "status": "attending_only",
        "status_note": "Gary missed the reply window with Soniya; snack-table serving slot is no longer available. He still has a free pass to attend as a guest. Reconnaissance mission — walk the floor, note conversations, gather signal.",
        "date": "2026-06-12",
        "end_date": "2026-06-12",
        "start_time": "11:00",
        "end_time": "17:00",
        "timezone": "America/Los_Angeles",
        "venue": "ICC, 525 Los Coches St, Milpitas, CA 95035",
        "city": "Milpitas, CA",
        "host": {
          "name": "Soniya",
          "org": "SF Tech Fest"
        },
        "format": "Pass-only attendance. No serving. Gary attends as a guest with a free pass, walks the floor, and gathers signal.",
        "products": [],
        "qr_codes": [],
        "owner": "Gary",
        "next_milestone": {
          "phase": 5,
          "due": "2026-06-13",
          "what": "Post-event: note any conversations or observations from the floor"
        },
        "reminders": {
          "apple_reminder": false,
          "apple_calendar": null,
          "check_in_date": null
        },
        "docs": {
          "checklist": null,
          "proposal": "proposal.md",
          "roadmap": "implementation_roadmap.md",
          "field_assets": null
        },
        "links": {
          "luma": "https://luma.com/sftechfest26",
          "website": "https://sftechfest.com/"
        },
        "path": "sftechfestjune26"
      },
      {
        "schema_version": 1,
        "slug": "onsenglobalforumjune23",
        "name": "Onsen Global Leaders Forum 2026",
        "status": "planning",
        "status_note": "Format set (≈20 sealed co-branded cacao-tea bags in a basket, no pour); Phase 0 pending with Tiffine (logo, table placement, registration).",
        "date": "2026-06-23",
        "end_date": "2026-06-23",
        "start_time": "17:30",
        "end_time": "19:30",
        "timezone": "America/Los_Angeles",
        "venue": "Japan Innovation Campus, Palo Alto, CA",
        "city": "Palo Alto, CA",
        "host": {
          "name": "Tiffine",
          "org": "Onsen Global"
        },
        "format": "≈20 individually sealed cacao-tea bags in a small basket on the snack table, each label co-branded Onsen Global × Agroverse with a provenance QR. No flasks, no pour, no booth.",
        "products": [
          "Paulo's cacao tea (Pará)"
        ],
        "qr_codes": [
          {
            "id": "OGLF_CT_20260623_1",
            "landing": "agl8",
            "product": "Paulo's cacao tea",
            "status": "pending"
          }
        ],
        "owner": "Gary",
        "next_milestone": {
          "phase": 0,
          "due": "2026-06-16",
          "what": "Confirm logo / table placement / registration with Tiffine"
        },
        "reminders": {
          "apple_reminder": false,
          "apple_calendar": null,
          "check_in_date": null
        },
        "docs": {
          "checklist": "EXECUTION_CHECKLIST.md",
          "proposal": "proposal.md",
          "roadmap": "implementation_roadmap.md"
        },
        "links": {
          "luma": "https://luma.com/tw8r8xp3"
        },
        "path": "onsenglobalforumjune23"
      },
      {
        "schema_version": 1,
        "slug": "dualtechsummitjune26",
        "name": "Dual Tech Summit 2026",
        "status": "planning",
        "status_note": "Venue + Kirsten pre-brew confirmed; date/table/ClawCamp timing pending with Ken (check-in May 27).",
        "date": "2026-06-26",
        "end_date": "2026-06-26",
        "start_time": null,
        "end_time": null,
        "timezone": "America/Los_Angeles",
        "venue": "War Memorial Veterans Building, San Francisco, CA",
        "city": "San Francisco, CA",
        "host": {
          "name": "Ken",
          "org": "Orbis86 / ClawCamp (SVH Capital Dual Tech Summit)"
        },
        "format": "Two flasks — Oscar's ceremonial cacao + Paulo's cacao tea — 3 oz cups, poured at a table Ken provides.",
        "products": [
          "Oscar's ceremonial cacao (Bahia)",
          "Paulo's cacao tea (Pará)"
        ],
        "qr_codes": [
          {
            "id": "DTS_CC_20260626_1",
            "landing": "agl4",
            "product": "Oscar's ceremonial cacao",
            "status": "minted"
          },
          {
            "id": "DTS_CT_20260626_1",
            "landing": "agl8",
            "product": "Paulo's cacao tea",
            "status": "minted"
          }
        ],
        "owner": "Gary",
        "next_milestone": {
          "phase": 0,
          "due": "2026-05-31",
          "what": "Confirm date / table / ClawCamp timing with Ken"
        },
        "reminders": {
          "apple_reminder": true,
          "apple_calendar": "Work",
          "check_in_date": "2026-05-27"
        },
        "docs": {
          "checklist": "EXECUTION_CHECKLIST.md",
          "proposal": "proposal_finalized.md",
          "roadmap": "implementation_roadmap.md",
          "field_assets": "field_assets.md"
        },
        "links": {
          "luma": "https://luma.com/dualtechsummitjune26"
        },
        "path": "dualtechsummitjune26"
      }
    ]
  },
  "past": {
    "source": "agroverse_shop/event-details-registration",
    "source_ref": "local:/Users/garyjob/Applications/market_research/events/../../agroverse_shop/event-details-registration/events.json",
    "count": 29,
    "date_review_needed": [
      "cacao-circle-anchoring-resilience-with-agroverse",
      "cacao-circle-grounding-growth-with-agroverse",
      "mantra-fire-cacao-circle-with-hudost",
      "agroverse-sip-savor-restore-with-sustainable-cacao-at-sf-climate-week-sonoma-county",
      "cacao-circle-at-regen-house-in-london-on-climate-action-week-2025",
      "agroverse-cacao-circle-at-better-daze-festival-2025",
      "cacao-circle-at-better-daze-festival-2024",
      "cacao-circle-at-mings-lounge",
      "cacao-circle-at-soha-summer-festiva",
      "one-cacao-at-a-time-geopolitics-your-craft",
      "agroverse-cacao-circle-ai-web3-founders-mixer-regenerating-the-amazon-with-tech-visionaries",
      "cacao-circle-at-create-the-future-summit-2025",
      "cacao-circle-at-eth-sf-after-hours-with-crypto-underground-x-stand-with-crypto-cali-tour",
      "join-our-cacao-circle-at-orbis86-eth-sf-the-future-of-tech-ai-x-web3",
      "under-the-seven-sistars-cacao-circle",
      "agroverse-cacao-circle-regenerating-the-amazon-rainforest-with-the-underdog-founders",
      "cacao-circle-at-the-climate-hub-savoring-sustainability-from-the-amazon-rainforest",
      "cacao-circle-at-the-social-innovation-hub-uplifting-minds-and-hearts-with-regenerative-cacao",
      "cacao-circle-at-okanogan-fall-barter-faire-2025",
      "cacao-circle-at-okanogan-family-faire-spring-barter-faire-2025"
    ],
    "events": [
      {
        "slug": "cacao-circle-anchoring-resilience-with-agroverse",
        "title": "Mantra Fire Cacao Circle with HuDost",
        "status": "past",
        "date": "2025-07-16",
        "date_displayed": "July 16, 2025 at 06:00 PM",
        "time": "06:00 PM",
        "date_source": "page-meta",
        "date_confidence": "low",
        "location": "Corvallis",
        "url": "https://agroverse.shop/event-details-registration/cacao-circle-anchoring-resilience-with-agroverse/",
        "rsvp_url": null,
        "description": "width=device-width, initial-scale=1.0\" name=\"viewport\"/>\n<meta content=\"IE=edge\" http-equiv=\"X-UA-Compatible\"/>\n<!-- SEO Meta Tags -->\n<title>Mantra Fire Cacao Circle with HuDost | Agroverse</title>\n<meta content=\"Experience a soulful cacao circle with HuDost and Johanna Beekman at Mantra Fire, blending heart-opening cacao rituals with neo-folk-world-rock music in the vibrant community of Corvallis, Oregon.",
        "image": "width=device-width, initial-scale=1.0\" name=\"viewport\"/>\n<meta content=\"IE=edge\" http-equiv=\"X-UA-Compatible\"/>\n<!-- SEO Meta Tags -->\n<title>Mantra Fire Cacao Circle with HuDost | Agroverse</title>\n<meta content=\"Experience a soulful cacao circle with HuDost and Johanna Beekman at Mantra Fire, blending heart-opening cacao rituals with neo-folk-world-rock music in the vibrant community of Corvallis, Oregon.\" name=\"description\"/>\n<link href=\"https://www.agroverse.shop/event-details-registration/cacao-circle-anchoring-resilience-with-agroverse\" rel=\"canonical\"/>\n<!-- Open Graph / Facebook -->\n<meta content=\"website\" property=\"og:type\"/>\n<meta content=\"https://www.agroverse.shop/event-details-registration/cacao-circle-anchoring-resilience-with-agroverse\" property=\"og:url\"/>\n<meta content=\"Mantra Fire Cacao Circle with HuDost | Agroverse | Agroverse\" property=\"og:title\"/>\n<meta content=\"Experience a soulful cacao circle with HuDost and Johanna Beekman at Mantra Fire, blending heart-opening cacao rituals with neo-folk-world-rock music in the vibrant community of Corvallis, Oregon.\" property=\"og:description\"/>\n<meta content=\"https://static.wixstatic.com/media/0e2cde_b415a17906f84f25a55ad57a6c996590~mv2.jpeg/v1/fill/w_946,h_2048,al_c,q_85/0e2cde_b415a17906f84f25a55ad57a6c996590~mv2.jpeg"
      },
      {
        "slug": "cacao-circle-grounding-growth-with-agroverse",
        "title": "Mantra Fire Cacao Circle with HuDost",
        "status": "past",
        "date": "2025-07-16",
        "date_displayed": "July 16, 2025 at 06:00 PM",
        "time": "06:00 PM",
        "date_source": "page-meta",
        "date_confidence": "low",
        "location": "Corvallis",
        "url": "https://agroverse.shop/event-details-registration/cacao-circle-grounding-growth-with-agroverse/",
        "rsvp_url": null,
        "description": "width=device-width, initial-scale=1.0\" name=\"viewport\"/>\n<meta content=\"IE=edge\" http-equiv=\"X-UA-Compatible\"/>\n<!-- SEO Meta Tags -->\n<title>Mantra Fire Cacao Circle with HuDost | Agroverse</title>\n<meta content=\"Experience a soulful cacao circle with HuDost and Johanna Beekman at Mantra Fire, blending heart-opening cacao rituals with neo-folk-world-rock music in the vibrant community of Corvallis, Oregon.",
        "image": "width=device-width, initial-scale=1.0\" name=\"viewport\"/>\n<meta content=\"IE=edge\" http-equiv=\"X-UA-Compatible\"/>\n<!-- SEO Meta Tags -->\n<title>Mantra Fire Cacao Circle with HuDost | Agroverse</title>\n<meta content=\"Experience a soulful cacao circle with HuDost and Johanna Beekman at Mantra Fire, blending heart-opening cacao rituals with neo-folk-world-rock music in the vibrant community of Corvallis, Oregon.\" name=\"description\"/>\n<link href=\"https://www.agroverse.shop/event-details-registration/cacao-circle-grounding-growth-with-agroverse\" rel=\"canonical\"/>\n<!-- Open Graph / Facebook -->\n<meta content=\"website\" property=\"og:type\"/>\n<meta content=\"https://www.agroverse.shop/event-details-registration/cacao-circle-grounding-growth-with-agroverse\" property=\"og:url\"/>\n<meta content=\"Mantra Fire Cacao Circle with HuDost | Agroverse | Agroverse\" property=\"og:title\"/>\n<meta content=\"Experience a soulful cacao circle with HuDost and Johanna Beekman at Mantra Fire, blending heart-opening cacao rituals with neo-folk-world-rock music in the vibrant community of Corvallis, Oregon.\" property=\"og:description\"/>\n<meta content=\"https://static.wixstatic.com/media/0e2cde_b415a17906f84f25a55ad57a6c996590~mv2.jpeg/v1/fill/w_946,h_2048,al_c,q_85/0e2cde_b415a17906f84f25a55ad57a6c996590~mv2.jpeg"
      },
      {
        "slug": "mantra-fire-cacao-circle-with-hudost",
        "title": "Mantra Fire Cacao Circle with HuDost",
        "status": "past",
        "date": "2025-07-16",
        "date_displayed": "July 16, 2025 at 06:00 PM",
        "time": "06:00 PM",
        "date_source": "page-meta",
        "date_confidence": "low",
        "location": "Corvallis",
        "url": "https://agroverse.shop/event-details-registration/mantra-fire-cacao-circle-with-hudost/",
        "rsvp_url": null,
        "description": "width=device-width, initial-scale=1.0\" name=\"viewport\"/>\n<meta content=\"IE=edge\" http-equiv=\"X-UA-Compatible\"/>\n<!-- SEO Meta Tags -->\n<title>Mantra Fire Cacao Circle with HuDost | Agroverse</title>\n<meta content=\"Experience a soulful cacao circle with HuDost and Johanna Beekman at Mantra Fire, blending heart-opening cacao rituals with neo-folk-world-rock music in the vibrant community of Corvallis, Oregon.",
        "image": "width=device-width, initial-scale=1.0\" name=\"viewport\"/>\n<meta content=\"IE=edge\" http-equiv=\"X-UA-Compatible\"/>\n<!-- SEO Meta Tags -->\n<title>Mantra Fire Cacao Circle with HuDost | Agroverse</title>\n<meta content=\"Experience a soulful cacao circle with HuDost and Johanna Beekman at Mantra Fire, blending heart-opening cacao rituals with neo-folk-world-rock music in the vibrant community of Corvallis, Oregon.\" name=\"description\"/>\n<link href=\"https://www.agroverse.shop/event-details-registration/mantra-fire-cacao-circle-with-hudost\" rel=\"canonical\"/>\n<!-- Open Graph / Facebook -->\n<meta content=\"website\" property=\"og:type\"/>\n<meta content=\"https://www.agroverse.shop/event-details-registration/mantra-fire-cacao-circle-with-hudost\" property=\"og:url\"/>\n<meta content=\"Mantra Fire Cacao Circle with HuDost | Agroverse | Agroverse\" property=\"og:title\"/>\n<meta content=\"Experience a soulful cacao circle with HuDost and Johanna Beekman at Mantra Fire, blending heart-opening cacao rituals with neo-folk-world-rock music in the vibrant community of Corvallis, Oregon.\" property=\"og:description\"/>\n<meta content=\"https://static.wixstatic.com/media/0e2cde_b415a17906f84f25a55ad57a6c996590~mv2.jpeg/v1/fill/w_946,h_2048,al_c,q_85/0e2cde_b415a17906f84f25a55ad57a6c996590~mv2.jpeg"
      },
      {
        "slug": "agroverse-sip-savor-restore-with-sustainable-cacao-at-sf-climate-week-sonoma-county",
        "title": "Cacao Circle at Regen House in London on Climate Action Week 2025",
        "status": "past",
        "date": "2025-06-27",
        "date_displayed": "June 27, 2025 at 10:30 AM",
        "time": "10:30 AM",
        "date_source": "page-meta",
        "date_confidence": "low",
        "location": "London",
        "url": "https://agroverse.shop/event-details-registration/agroverse-sip-savor-restore-with-sustainable-cacao-at-sf-climate-week-sonoma-county/",
        "rsvp_url": null,
        "description": "width=device-width, initial-scale=1.0\" name=\"viewport\"/>\n<meta content=\"IE=edge\" http-equiv=\"X-UA-Compatible\"/>\n<!-- SEO Meta Tags -->\n<title>Cacao Circle at Regen House in London on Climate Action Week 2025 | Agroverse</title>\n<meta content=\"Join us at Regen House during London Climate Action Week for an intimate Cacao Circle, where the ancient wisdom of cacao meets modern climate action. Connect with like-minded changemakers, share intentions, and co-create a vision for a regenerative future—all in the vibrant setting of the iconic Min",
        "image": "width=device-width, initial-scale=1.0\" name=\"viewport\"/>\n<meta content=\"IE=edge\" http-equiv=\"X-UA-Compatible\"/>\n<!-- SEO Meta Tags -->\n<title>Cacao Circle at Regen House in London on Climate Action Week 2025 | Agroverse</title>\n<meta content=\"Join us at Regen House during London Climate Action Week for an intimate Cacao Circle, where the ancient wisdom of cacao meets modern climate action. Connect with like-minded changemakers, share intentions, and co-create a vision for a regenerative future—all in the vibrant setting of the iconic Min\" name=\"description\"/>\n<link href=\"https://www.agroverse.shop/event-details-registration/agroverse-sip-savor-restore-with-sustainable-cacao-at-sf-climate-week-sonoma-county\" rel=\"canonical\"/>\n<!-- Open Graph / Facebook -->\n<meta content=\"website\" property=\"og:type\"/>\n<meta content=\"https://www.agroverse.shop/event-details-registration/agroverse-sip-savor-restore-with-sustainable-cacao-at-sf-climate-week-sonoma-county\" property=\"og:url\"/>\n<meta content=\"Cacao Circle at Regen House in London on Climate Action Week 2025 | Agroverse | Agroverse\" property=\"og:title\"/>\n<meta content=\"Join us at Regen House during London Climate Action Week for an intimate Cacao Circle, where the ancient wisdom of cacao meets modern climate action. Connect with like-minded changemakers, share intentions, and co-create a vision for a regenerative future—all in the vibrant setting of the iconic Min\" property=\"og:description\"/>\n<meta content=\"https://static.wixstatic.com/media/0e2cde_670521c7cd164b76a9afe757ca47f3fd~mv2.png/v1/fill/w_1104,h_1404,al_c/0e2cde_670521c7cd164b76a9afe757ca47f3fd~mv2.png"
      },
      {
        "slug": "cacao-circle-at-regen-house-in-london-on-climate-action-week-2025",
        "title": "Cacao Circle at Regen House in London on Climate Action Week 2025",
        "status": "past",
        "date": "2025-06-27",
        "date_displayed": "June 27, 2025 at 10:30 AM",
        "time": "10:30 AM",
        "date_source": "page-meta",
        "date_confidence": "low",
        "location": "London",
        "url": "https://agroverse.shop/event-details-registration/cacao-circle-at-regen-house-in-london-on-climate-action-week-2025/",
        "rsvp_url": null,
        "description": "width=device-width, initial-scale=1.0\" name=\"viewport\"/>\n<meta content=\"IE=edge\" http-equiv=\"X-UA-Compatible\"/>\n<!-- SEO Meta Tags -->\n<title>Cacao Circle at Regen House in London on Climate Action Week 2025 | Agroverse</title>\n<meta content=\"Join us at Regen House during London Climate Action Week for an intimate Cacao Circle, where the ancient wisdom of cacao meets modern climate action. Connect with like-minded changemakers, share intentions, and co-create a vision for a regenerative future—all in the vibrant setting of the iconic Min",
        "image": "width=device-width, initial-scale=1.0\" name=\"viewport\"/>\n<meta content=\"IE=edge\" http-equiv=\"X-UA-Compatible\"/>\n<!-- SEO Meta Tags -->\n<title>Cacao Circle at Regen House in London on Climate Action Week 2025 | Agroverse</title>\n<meta content=\"Join us at Regen House during London Climate Action Week for an intimate Cacao Circle, where the ancient wisdom of cacao meets modern climate action. Connect with like-minded changemakers, share intentions, and co-create a vision for a regenerative future—all in the vibrant setting of the iconic Min\" name=\"description\"/>\n<link href=\"https://www.agroverse.shop/event-details-registration/cacao-circle-at-regen-house-in-london-on-climate-action-week-2025\" rel=\"canonical\"/>\n<!-- Open Graph / Facebook -->\n<meta content=\"website\" property=\"og:type\"/>\n<meta content=\"https://www.agroverse.shop/event-details-registration/cacao-circle-at-regen-house-in-london-on-climate-action-week-2025\" property=\"og:url\"/>\n<meta content=\"Cacao Circle at Regen House in London on Climate Action Week 2025 | Agroverse | Agroverse\" property=\"og:title\"/>\n<meta content=\"Join us at Regen House during London Climate Action Week for an intimate Cacao Circle, where the ancient wisdom of cacao meets modern climate action. Connect with like-minded changemakers, share intentions, and co-create a vision for a regenerative future—all in the vibrant setting of the iconic Min\" property=\"og:description\"/>\n<meta content=\"https://static.wixstatic.com/media/0e2cde_670521c7cd164b76a9afe757ca47f3fd~mv2.png/v1/fill/w_1104,h_1404,al_c/0e2cde_670521c7cd164b76a9afe757ca47f3fd~mv2.png"
      },
      {
        "slug": "agroverse-cacao-circle-at-rebel-market-outpost",
        "title": "Agroverse Cacao Circle at Rebel Market Outpost",
        "status": "past",
        "date": "2025-06-25",
        "date_displayed": "June 25, 2025 at 05:00 PM",
        "time": "05:00 PM",
        "date_source": "page-meta",
        "date_confidence": "medium",
        "location": "Seattle",
        "url": "https://agroverse.shop/event-details-registration/agroverse-cacao-circle-at-rebel-market-outpost/",
        "rsvp_url": null,
        "description": "width=device-width, initial-scale=1.0\" name=\"viewport\"/>\n<meta content=\"IE=edge\" http-equiv=\"X-UA-Compatible\"/>\n<!-- SEO Meta Tags -->\n<title>Agroverse Cacao Circle at Rebel Market Outpost | Agroverse</title>\n<meta content=\"Join us dockside in Seattle on June 25th for an Agroverse Cacao Circle at the vibrant Rebel Market Outpost! Sip ethically sourced Amazon cacao, connect with rebels and mystics, and support rainforest regeneration under the solstice sky. 45% of every cacao bag sold empowers organic farmers and plants",
        "image": "width=device-width, initial-scale=1.0\" name=\"viewport\"/>\n<meta content=\"IE=edge\" http-equiv=\"X-UA-Compatible\"/>\n<!-- SEO Meta Tags -->\n<title>Agroverse Cacao Circle at Rebel Market Outpost | Agroverse</title>\n<meta content=\"Join us dockside in Seattle on June 25th for an Agroverse Cacao Circle at the vibrant Rebel Market Outpost! Sip ethically sourced Amazon cacao, connect with rebels and mystics, and support rainforest regeneration under the solstice sky. 45% of every cacao bag sold empowers organic farmers and plants\" name=\"description\"/>\n<link href=\"https://www.agroverse.shop/event-details-registration/agroverse-cacao-circle-at-rebel-market-outpost\" rel=\"canonical\"/>\n<!-- Open Graph / Facebook -->\n<meta content=\"website\" property=\"og:type\"/>\n<meta content=\"https://www.agroverse.shop/event-details-registration/agroverse-cacao-circle-at-rebel-market-outpost\" property=\"og:url\"/>\n<meta content=\"Agroverse Cacao Circle at Rebel Market Outpost | Agroverse | Agroverse\" property=\"og:title\"/>\n<meta content=\"Join us dockside in Seattle on June 25th for an Agroverse Cacao Circle at the vibrant Rebel Market Outpost! Sip ethically sourced Amazon cacao, connect with rebels and mystics, and support rainforest regeneration under the solstice sky. 45% of every cacao bag sold empowers organic farmers and plants\" property=\"og:description\"/>\n<meta content=\"https://static.wixstatic.com/media/0e2cde_a03abc9709b2402f9239d1ac62f23b94~mv2.jpg/v1/fill/w_1024,h_918,al_c,q_85/0e2cde_a03abc9709b2402f9239d1ac62f23b94~mv2.jpg"
      },
      {
        "slug": "agroverse-cacao-circle-at-better-daze-festival-2025",
        "title": "Agroverse Cacao Circle at Better Daze Festival 2025",
        "status": "past",
        "date": "2025-06-13",
        "date_displayed": "June 13, 2025 at 03:00 PM",
        "time": "03:00 PM",
        "date_source": "page-meta",
        "date_confidence": "low",
        "location": "Springdale",
        "url": "https://agroverse.shop/event-details-registration/agroverse-cacao-circle-at-better-daze-festival-2025/",
        "rsvp_url": null,
        "description": "width=device-width, initial-scale=1.0\" name=\"viewport\"/>\n<meta content=\"IE=edge\" http-equiv=\"X-UA-Compatible\"/>\n<!-- SEO Meta Tags -->\n<title>Agroverse Cacao Circle at Better Daze Festival 2025 | Agroverse</title>\n<meta content=\"Join Agroverse at the Better Daze Festival for a soulful Cacao Circle, connecting hearts and honoring the Amazon through ethically sourced cacao.",
        "image": "width=device-width, initial-scale=1.0\" name=\"viewport\"/>\n<meta content=\"IE=edge\" http-equiv=\"X-UA-Compatible\"/>\n<!-- SEO Meta Tags -->\n<title>Agroverse Cacao Circle at Better Daze Festival 2025 | Agroverse</title>\n<meta content=\"Join Agroverse at the Better Daze Festival for a soulful Cacao Circle, connecting hearts and honoring the Amazon through ethically sourced cacao.\" name=\"description\"/>\n<link href=\"https://www.agroverse.shop/event-details-registration/agroverse-cacao-circle-at-better-daze-festival-2025\" rel=\"canonical\"/>\n<!-- Open Graph / Facebook -->\n<meta content=\"website\" property=\"og:type\"/>\n<meta content=\"https://www.agroverse.shop/event-details-registration/agroverse-cacao-circle-at-better-daze-festival-2025\" property=\"og:url\"/>\n<meta content=\"Agroverse Cacao Circle at Better Daze Festival 2025 | Agroverse | Agroverse\" property=\"og:title\"/>\n<meta content=\"Join Agroverse at the Better Daze Festival for a soulful Cacao Circle, connecting hearts and honoring the Amazon through ethically sourced cacao.\" property=\"og:description\"/>\n<meta content=\"https://static.wixstatic.com/media/0e2cde_48b3f2c376604fac90fe8d724bcb5788~mv2.jpg/v1/fill/w_3089,h_1356,al_c,q_90/0e2cde_48b3f2c376604fac90fe8d724bcb5788~mv2.jpg"
      },
      {
        "slug": "cacao-circle-at-better-daze-festival-2024",
        "title": "Agroverse Cacao Circle at Better Daze Festival 2025",
        "status": "past",
        "date": "2025-06-13",
        "date_displayed": "June 13, 2025 at 03:00 PM",
        "time": "03:00 PM",
        "date_source": "page-meta",
        "date_confidence": "low",
        "location": "Springdale",
        "url": "https://agroverse.shop/event-details-registration/cacao-circle-at-better-daze-festival-2024/",
        "rsvp_url": null,
        "description": "width=device-width, initial-scale=1.0\" name=\"viewport\"/>\n<meta content=\"IE=edge\" http-equiv=\"X-UA-Compatible\"/>\n<!-- SEO Meta Tags -->\n<title>Agroverse Cacao Circle at Better Daze Festival 2025 | Agroverse</title>\n<meta content=\"Join Agroverse at the Better Daze Festival for a soulful Cacao Circle, connecting hearts and honoring the Amazon through ethically sourced cacao.",
        "image": "width=device-width, initial-scale=1.0\" name=\"viewport\"/>\n<meta content=\"IE=edge\" http-equiv=\"X-UA-Compatible\"/>\n<!-- SEO Meta Tags -->\n<title>Agroverse Cacao Circle at Better Daze Festival 2025 | Agroverse</title>\n<meta content=\"Join Agroverse at the Better Daze Festival for a soulful Cacao Circle, connecting hearts and honoring the Amazon through ethically sourced cacao.\" name=\"description\"/>\n<link href=\"https://www.agroverse.shop/event-details-registration/cacao-circle-at-better-daze-festival-2024\" rel=\"canonical\"/>\n<!-- Open Graph / Facebook -->\n<meta content=\"website\" property=\"og:type\"/>\n<meta content=\"https://www.agroverse.shop/event-details-registration/cacao-circle-at-better-daze-festival-2024\" property=\"og:url\"/>\n<meta content=\"Agroverse Cacao Circle at Better Daze Festival 2025 | Agroverse | Agroverse\" property=\"og:title\"/>\n<meta content=\"Join Agroverse at the Better Daze Festival for a soulful Cacao Circle, connecting hearts and honoring the Amazon through ethically sourced cacao.\" property=\"og:description\"/>\n<meta content=\"https://static.wixstatic.com/media/0e2cde_48b3f2c376604fac90fe8d724bcb5788~mv2.jpg/v1/fill/w_3089,h_1356,al_c,q_90/0e2cde_48b3f2c376604fac90fe8d724bcb5788~mv2.jpg"
      },
      {
        "slug": "cacao-circle-at-mings-lounge",
        "title": "Agroverse Cacao Circle at Better Daze Festival 2025",
        "status": "past",
        "date": "2025-06-13",
        "date_displayed": "June 13, 2025 at 03:00 PM",
        "time": "03:00 PM",
        "date_source": "page-meta",
        "date_confidence": "low",
        "location": "Springdale",
        "url": "https://agroverse.shop/event-details-registration/cacao-circle-at-mings-lounge/",
        "rsvp_url": null,
        "description": "width=device-width, initial-scale=1.0\" name=\"viewport\"/>\n<meta content=\"IE=edge\" http-equiv=\"X-UA-Compatible\"/>\n<!-- SEO Meta Tags -->\n<title>Agroverse Cacao Circle at Better Daze Festival 2025 | Agroverse</title>\n<meta content=\"Join Agroverse at the Better Daze Festival for a soulful Cacao Circle, connecting hearts and honoring the Amazon through ethically sourced cacao.",
        "image": "width=device-width, initial-scale=1.0\" name=\"viewport\"/>\n<meta content=\"IE=edge\" http-equiv=\"X-UA-Compatible\"/>\n<!-- SEO Meta Tags -->\n<title>Agroverse Cacao Circle at Better Daze Festival 2025 | Agroverse</title>\n<meta content=\"Join Agroverse at the Better Daze Festival for a soulful Cacao Circle, connecting hearts and honoring the Amazon through ethically sourced cacao.\" name=\"description\"/>\n<link href=\"https://www.agroverse.shop/event-details-registration/cacao-circle-at-mings-lounge\" rel=\"canonical\"/>\n<!-- Open Graph / Facebook -->\n<meta content=\"website\" property=\"og:type\"/>\n<meta content=\"https://www.agroverse.shop/event-details-registration/cacao-circle-at-mings-lounge\" property=\"og:url\"/>\n<meta content=\"Agroverse Cacao Circle at Better Daze Festival 2025 | Agroverse | Agroverse\" property=\"og:title\"/>\n<meta content=\"Join Agroverse at the Better Daze Festival for a soulful Cacao Circle, connecting hearts and honoring the Amazon through ethically sourced cacao.\" property=\"og:description\"/>\n<meta content=\"https://static.wixstatic.com/media/0e2cde_48b3f2c376604fac90fe8d724bcb5788~mv2.jpg/v1/fill/w_3089,h_1356,al_c,q_90/0e2cde_48b3f2c376604fac90fe8d724bcb5788~mv2.jpg"
      },
      {
        "slug": "cacao-circle-at-soha-summer-festiva",
        "title": "Agroverse Cacao Circle at Better Daze Festival 2025",
        "status": "past",
        "date": "2025-06-13",
        "date_displayed": "June 13, 2025 at 03:00 PM",
        "time": "03:00 PM",
        "date_source": "page-meta",
        "date_confidence": "low",
        "location": "Springdale",
        "url": "https://agroverse.shop/event-details-registration/cacao-circle-at-soha-summer-festiva/",
        "rsvp_url": null,
        "description": "width=device-width, initial-scale=1.0\" name=\"viewport\"/>\n<meta content=\"IE=edge\" http-equiv=\"X-UA-Compatible\"/>\n<!-- SEO Meta Tags -->\n<title>Agroverse Cacao Circle at Better Daze Festival 2025 | Agroverse</title>\n<meta content=\"Join Agroverse at the Better Daze Festival for a soulful Cacao Circle, connecting hearts and honoring the Amazon through ethically sourced cacao.",
        "image": "width=device-width, initial-scale=1.0\" name=\"viewport\"/>\n<meta content=\"IE=edge\" http-equiv=\"X-UA-Compatible\"/>\n<!-- SEO Meta Tags -->\n<title>Agroverse Cacao Circle at Better Daze Festival 2025 | Agroverse</title>\n<meta content=\"Join Agroverse at the Better Daze Festival for a soulful Cacao Circle, connecting hearts and honoring the Amazon through ethically sourced cacao.\" name=\"description\"/>\n<link href=\"https://www.agroverse.shop/event-details-registration/cacao-circle-at-soha-summer-festiva\" rel=\"canonical\"/>\n<!-- Open Graph / Facebook -->\n<meta content=\"website\" property=\"og:type\"/>\n<meta content=\"https://www.agroverse.shop/event-details-registration/cacao-circle-at-soha-summer-festiva\" property=\"og:url\"/>\n<meta content=\"Agroverse Cacao Circle at Better Daze Festival 2025 | Agroverse | Agroverse\" property=\"og:title\"/>\n<meta content=\"Join Agroverse at the Better Daze Festival for a soulful Cacao Circle, connecting hearts and honoring the Amazon through ethically sourced cacao.\" property=\"og:description\"/>\n<meta content=\"https://static.wixstatic.com/media/0e2cde_48b3f2c376604fac90fe8d724bcb5788~mv2.jpg/v1/fill/w_3089,h_1356,al_c,q_90/0e2cde_48b3f2c376604fac90fe8d724bcb5788~mv2.jpg"
      },
      {
        "slug": "one-cacao-at-a-time-geopolitics-your-craft",
        "title": "Agroverse Cacao Circle at Better Daze Festival 2025",
        "status": "past",
        "date": "2025-06-13",
        "date_displayed": "June 13, 2025 at 03:00 PM",
        "time": "03:00 PM",
        "date_source": "page-meta",
        "date_confidence": "low",
        "location": "Springdale",
        "url": "https://agroverse.shop/event-details-registration/one-cacao-at-a-time-geopolitics-your-craft/",
        "rsvp_url": null,
        "description": "width=device-width, initial-scale=1.0\" name=\"viewport\"/>\n<meta content=\"IE=edge\" http-equiv=\"X-UA-Compatible\"/>\n<!-- SEO Meta Tags -->\n<title>Agroverse Cacao Circle at Better Daze Festival 2025 | Agroverse</title>\n<meta content=\"Join Agroverse at the Better Daze Festival for a soulful Cacao Circle, connecting hearts and honoring the Amazon through ethically sourced cacao.",
        "image": "width=device-width, initial-scale=1.0\" name=\"viewport\"/>\n<meta content=\"IE=edge\" http-equiv=\"X-UA-Compatible\"/>\n<!-- SEO Meta Tags -->\n<title>Agroverse Cacao Circle at Better Daze Festival 2025 | Agroverse</title>\n<meta content=\"Join Agroverse at the Better Daze Festival for a soulful Cacao Circle, connecting hearts and honoring the Amazon through ethically sourced cacao.\" name=\"description\"/>\n<link href=\"https://www.agroverse.shop/event-details-registration/one-cacao-at-a-time-geopolitics-your-craft\" rel=\"canonical\"/>\n<!-- Open Graph / Facebook -->\n<meta content=\"website\" property=\"og:type\"/>\n<meta content=\"https://www.agroverse.shop/event-details-registration/one-cacao-at-a-time-geopolitics-your-craft\" property=\"og:url\"/>\n<meta content=\"Agroverse Cacao Circle at Better Daze Festival 2025 | Agroverse | Agroverse\" property=\"og:title\"/>\n<meta content=\"Join Agroverse at the Better Daze Festival for a soulful Cacao Circle, connecting hearts and honoring the Amazon through ethically sourced cacao.\" property=\"og:description\"/>\n<meta content=\"https://static.wixstatic.com/media/0e2cde_48b3f2c376604fac90fe8d724bcb5788~mv2.jpg/v1/fill/w_3089,h_1356,al_c,q_90/0e2cde_48b3f2c376604fac90fe8d724bcb5788~mv2.jpg"
      },
      {
        "slug": "cacao-circle-at-wesfest-25",
        "title": "Cacao Circle at WesFest '25",
        "status": "past",
        "date": "2025-06-08",
        "date_displayed": "June 08, 2025 at 12:00 PM",
        "time": "12:00 PM",
        "date_source": "page-meta",
        "date_confidence": "medium",
        "location": "Ford",
        "url": "https://agroverse.shop/event-details-registration/cacao-circle-at-wesfest-25/",
        "rsvp_url": null,
        "description": "width=device-width, initial-scale=1.0\" name=\"viewport\"/>\n<meta content=\"IE=edge\" http-equiv=\"X-UA-Compatible\"/>\n<!-- SEO Meta Tags -->\n<title>Cacao Circle at WesFest '25 | Agroverse</title>\n<meta content=\"oin our cacao circle at WesFest '25! Taste cacao tea from Oscar’s Farm 2024 harvest and take home ceremonial cacao from Oscar’s and Sao Jorge’s 2024 harvests.",
        "image": "width=device-width, initial-scale=1.0\" name=\"viewport\"/>\n<meta content=\"IE=edge\" http-equiv=\"X-UA-Compatible\"/>\n<!-- SEO Meta Tags -->\n<title>Cacao Circle at WesFest '25 | Agroverse</title>\n<meta content=\"oin our cacao circle at WesFest '25! Taste cacao tea from Oscar’s Farm 2024 harvest and take home ceremonial cacao from Oscar’s and Sao Jorge’s 2024 harvests.\" name=\"description\"/>\n<link href=\"https://www.agroverse.shop/event-details-registration/cacao-circle-at-wesfest-25\" rel=\"canonical\"/>\n<!-- Open Graph / Facebook -->\n<meta content=\"website\" property=\"og:type\"/>\n<meta content=\"https://www.agroverse.shop/event-details-registration/cacao-circle-at-wesfest-25\" property=\"og:url\"/>\n<meta content=\"Cacao Circle at WesFest '25 | Agroverse | Agroverse\" property=\"og:title\"/>\n<meta content=\"oin our cacao circle at WesFest '25! Taste cacao tea from Oscar’s Farm 2024 harvest and take home ceremonial cacao from Oscar’s and Sao Jorge’s 2024 harvests.\" property=\"og:description\"/>\n<meta content=\"https://static.wixstatic.com/media/0e2cde_74dc262d03be418dba99454ce4b0132c~mv2.jpg/v1/fill/w_2048,h_1323,al_c,q_90/0e2cde_74dc262d03be418dba99454ce4b0132c~mv2.jpg"
      },
      {
        "slug": "cacao-circle-at-8th-annual-burning-cow-bart",
        "title": "Cacao Circle at 8th Annual Burning Cow Bart",
        "status": "past",
        "date": "2025-05-23",
        "date_displayed": "May 23, 2025 at 12:00 PM",
        "time": "12:00 PM",
        "date_source": "page-meta",
        "date_confidence": "medium",
        "location": "Springdale",
        "url": "https://agroverse.shop/event-details-registration/cacao-circle-at-8th-annual-burning-cow-bart/",
        "rsvp_url": null,
        "description": "width=device-width, initial-scale=1.0\" name=\"viewport\"/>\n<meta content=\"IE=edge\" http-equiv=\"X-UA-Compatible\"/>\n<!-- SEO Meta Tags -->\n<title>Cacao Circle at 8th Annual Burning Cow Bart | Agroverse</title>\n<meta content=\"Join our cacao circle at the Burning Cow Barter Fest! Savor cacao tea from Oscar’s Farm 2024 harvest and take home ceremonial cacao from Oscar’s and Sao Jorge’s 2024 harvests.",
        "image": "width=device-width, initial-scale=1.0\" name=\"viewport\"/>\n<meta content=\"IE=edge\" http-equiv=\"X-UA-Compatible\"/>\n<!-- SEO Meta Tags -->\n<title>Cacao Circle at 8th Annual Burning Cow Bart | Agroverse</title>\n<meta content=\"Join our cacao circle at the Burning Cow Barter Fest! Savor cacao tea from Oscar’s Farm 2024 harvest and take home ceremonial cacao from Oscar’s and Sao Jorge’s 2024 harvests.\" name=\"description\"/>\n<link href=\"https://www.agroverse.shop/event-details-registration/cacao-circle-at-8th-annual-burning-cow-bart\" rel=\"canonical\"/>\n<!-- Open Graph / Facebook -->\n<meta content=\"website\" property=\"og:type\"/>\n<meta content=\"https://www.agroverse.shop/event-details-registration/cacao-circle-at-8th-annual-burning-cow-bart\" property=\"og:url\"/>\n<meta content=\"Cacao Circle at 8th Annual Burning Cow Bart | Agroverse | Agroverse\" property=\"og:title\"/>\n<meta content=\"Join our cacao circle at the Burning Cow Barter Fest! Savor cacao tea from Oscar’s Farm 2024 harvest and take home ceremonial cacao from Oscar’s and Sao Jorge’s 2024 harvests.\" property=\"og:description\"/>\n<meta content=\"https://static.wixstatic.com/media/0e2cde_c0f90a46d7ab44d483c853fd48428707~mv2.jpg/v1/fill/w_927,h_1200,al_c,q_85/0e2cde_c0f90a46d7ab44d483c853fd48428707~mv2.jpg"
      },
      {
        "slug": "sacred-cacao-circle-heart-opening-townhall",
        "title": "Sacred Cacao Circle: Heart-Opening Townhall",
        "status": "past",
        "date": "2025-04-28",
        "date_displayed": "April 28, 2025 at 06:30 PM",
        "time": "06:30 PM",
        "date_source": "page-meta",
        "date_confidence": "medium",
        "location": "San Francisco",
        "url": "https://agroverse.shop/event-details-registration/sacred-cacao-circle-heart-opening-townhall/",
        "rsvp_url": null,
        "description": "width=device-width, initial-scale=1.0\" name=\"viewport\"/>\n<meta content=\"IE=edge\" http-equiv=\"X-UA-Compatible\"/>\n<!-- SEO Meta Tags -->\n<title>Sacred Cacao Circle: Heart-Opening Townhall | Agroverse</title>\n<meta content=\"Join us at Frontier Tower for a sacred cacao circle, woven into our 2nd Townhall celebration. Connect with our vibrant community through ceremonial cacao, shared stories, and the vision of our 16-floor vertical village.",
        "image": "width=device-width, initial-scale=1.0\" name=\"viewport\"/>\n<meta content=\"IE=edge\" http-equiv=\"X-UA-Compatible\"/>\n<!-- SEO Meta Tags -->\n<title>Sacred Cacao Circle: Heart-Opening Townhall | Agroverse</title>\n<meta content=\"Join us at Frontier Tower for a sacred cacao circle, woven into our 2nd Townhall celebration. Connect with our vibrant community through ceremonial cacao, shared stories, and the vision of our 16-floor vertical village.\" name=\"description\"/>\n<link href=\"https://www.agroverse.shop/event-details-registration/sacred-cacao-circle-heart-opening-townhall\" rel=\"canonical\"/>\n<!-- Open Graph / Facebook -->\n<meta content=\"website\" property=\"og:type\"/>\n<meta content=\"https://www.agroverse.shop/event-details-registration/sacred-cacao-circle-heart-opening-townhall\" property=\"og:url\"/>\n<meta content=\"Sacred Cacao Circle: Heart-Opening Townhall | Agroverse | Agroverse\" property=\"og:title\"/>\n<meta content=\"Join us at Frontier Tower for a sacred cacao circle, woven into our 2nd Townhall celebration. Connect with our vibrant community through ceremonial cacao, shared stories, and the vision of our 16-floor vertical village.\" property=\"og:description\"/>\n<meta content=\"https://static.wixstatic.com/media/0e2cde_4b91826527824bd08a44a693b0588eb9~mv2.avif/v1/fill/w_800,h_800,al_c/0e2cde_4b91826527824bd08a44a693b0588eb9~mv2.avif"
      },
      {
        "slug": "agroverse-cacao-circle-a-heart-centering-experience",
        "title": "Agroverse Cacao Circle: A Heart-Centering Experience",
        "status": "past",
        "date": "2025-04-22",
        "date_displayed": "April 22, 2025 at 05:30 PM",
        "time": "05:30 PM",
        "date_source": "page-meta",
        "date_confidence": "medium",
        "location": "San Francisco",
        "url": "https://agroverse.shop/event-details-registration/agroverse-cacao-circle-a-heart-centering-experience/",
        "rsvp_url": null,
        "description": "width=device-width, initial-scale=1.0\" name=\"viewport\"/>\n<meta content=\"IE=edge\" http-equiv=\"X-UA-Compatible\"/>\n<!-- SEO Meta Tags -->\n<title>Agroverse Cacao Circle: A Heart-Centering Experience | Agroverse</title>\n<meta content=\"Join us for a soulful cacao circle featuring ceremony-grade cacao sourced from sustainable Amazonian agroforestry, fostering connection and mindfulness at SF Climate Week.",
        "image": "width=device-width, initial-scale=1.0\" name=\"viewport\"/>\n<meta content=\"IE=edge\" http-equiv=\"X-UA-Compatible\"/>\n<!-- SEO Meta Tags -->\n<title>Agroverse Cacao Circle: A Heart-Centering Experience | Agroverse</title>\n<meta content=\"Join us for a soulful cacao circle featuring ceremony-grade cacao sourced from sustainable Amazonian agroforestry, fostering connection and mindfulness at SF Climate Week.\" name=\"description\"/>\n<link href=\"https://www.agroverse.shop/event-details-registration/agroverse-cacao-circle-a-heart-centering-experience\" rel=\"canonical\"/>\n<!-- Open Graph / Facebook -->\n<meta content=\"website\" property=\"og:type\"/>\n<meta content=\"https://www.agroverse.shop/event-details-registration/agroverse-cacao-circle-a-heart-centering-experience\" property=\"og:url\"/>\n<meta content=\"Agroverse Cacao Circle: A Heart-Centering Experience | Agroverse | Agroverse\" property=\"og:title\"/>\n<meta content=\"Join us for a soulful cacao circle featuring ceremony-grade cacao sourced from sustainable Amazonian agroforestry, fostering connection and mindfulness at SF Climate Week.\" property=\"og:description\"/>\n<meta content=\"https://static.wixstatic.com/media/0e2cde_51286f8e469543d98b238f557869c78e~mv2.avif/v1/fill/w_800,h_800,al_c/0e2cde_51286f8e469543d98b238f557869c78e~mv2.avif"
      },
      {
        "slug": "cacao-circle-at-orbis86-ai-x-web3-in-gaming-happy-hour-gdc",
        "title": "Cacao Circle at Orbis86: AI x Web3 in Gaming Happy Hour - GDC",
        "status": "past",
        "date": "2025-03-19",
        "date_displayed": "March 19, 2025 at 07:00 PM",
        "time": "07:00 PM",
        "date_source": "page-meta",
        "date_confidence": "medium",
        "location": "San Francisco",
        "url": "https://agroverse.shop/event-details-registration/cacao-circle-at-orbis86-ai-x-web3-in-gaming-happy-hour-gdc/",
        "rsvp_url": null,
        "description": "width=device-width, initial-scale=1.0\" name=\"viewport\"/>\n<meta content=\"IE=edge\" http-equiv=\"X-UA-Compatible\"/>\n<!-- SEO Meta Tags -->\n<title>Cacao Circle at Orbis86: AI x Web3 in Gaming Happy Hour - GDC | Agroverse</title>\n<meta content=\"Experience the transformative power of cacao during Orbis86's AI x Web3 in Gaming Happy Hour at GDC! Network, relax, and enjoy a unique cacao ceremony with industry pioneers.",
        "image": "width=device-width, initial-scale=1.0\" name=\"viewport\"/>\n<meta content=\"IE=edge\" http-equiv=\"X-UA-Compatible\"/>\n<!-- SEO Meta Tags -->\n<title>Cacao Circle at Orbis86: AI x Web3 in Gaming Happy Hour - GDC | Agroverse</title>\n<meta content=\"Experience the transformative power of cacao during Orbis86's AI x Web3 in Gaming Happy Hour at GDC! Network, relax, and enjoy a unique cacao ceremony with industry pioneers.\" name=\"description\"/>\n<link href=\"https://www.agroverse.shop/event-details-registration/cacao-circle-at-orbis86-ai-x-web3-in-gaming-happy-hour-gdc\" rel=\"canonical\"/>\n<!-- Open Graph / Facebook -->\n<meta content=\"website\" property=\"og:type\"/>\n<meta content=\"https://www.agroverse.shop/event-details-registration/cacao-circle-at-orbis86-ai-x-web3-in-gaming-happy-hour-gdc\" property=\"og:url\"/>\n<meta content=\"Cacao Circle at Orbis86: AI x Web3 in Gaming Happy Hour - GDC | Agroverse | Agroverse\" property=\"og:title\"/>\n<meta content=\"Experience the transformative power of cacao during Orbis86's AI x Web3 in Gaming Happy Hour at GDC! Network, relax, and enjoy a unique cacao ceremony with industry pioneers.\" property=\"og:description\"/>\n<meta content=\"https://static.wixstatic.com/media/0e2cde_416b49b440ed4bcdae0e5e3bbb432aee~mv2.jpg/v1/fill/w_1506,h_1502,al_c,q_90/0e2cde_416b49b440ed4bcdae0e5e3bbb432aee~mv2.jpg"
      },
      {
        "slug": "agroverse-cacao-circle-ai-web3-founders-mixer-regenerating-the-amazon-with-tech-visionaries",
        "title": "Join Our Cacao Circle at Orbis86: ETH SF! The Future of Tech: AI x Web3",
        "status": "past",
        "date": "2025-03-13",
        "date_displayed": "March 13, 2025 at 04:00 PM",
        "time": "04:00 PM",
        "date_source": "page-meta",
        "date_confidence": "low",
        "location": "San Francisco",
        "url": "https://agroverse.shop/event-details-registration/agroverse-cacao-circle-ai-web3-founders-mixer-regenerating-the-amazon-with-tech-visionaries/",
        "rsvp_url": null,
        "description": "width=device-width, initial-scale=1.0\" name=\"viewport\"/>\n<meta content=\"IE=edge\" http-equiv=\"X-UA-Compatible\"/>\n<!-- SEO Meta Tags -->\n<title>Join Our Cacao Circle at Orbis86: ETH SF! The Future of Tech: AI x Web3 | Agroverse</title>\n<meta content=\"Explore the intersection of Web3, AI, and sustainability with us!",
        "image": "width=device-width, initial-scale=1.0\" name=\"viewport\"/>\n<meta content=\"IE=edge\" http-equiv=\"X-UA-Compatible\"/>\n<!-- SEO Meta Tags -->\n<title>Join Our Cacao Circle at Orbis86: ETH SF! The Future of Tech: AI x Web3 | Agroverse</title>\n<meta content=\"Explore the intersection of Web3, AI, and sustainability with us!\" name=\"description\"/>\n<link href=\"https://www.agroverse.shop/event-details-registration/agroverse-cacao-circle-ai-web3-founders-mixer-regenerating-the-amazon-with-tech-visionaries\" rel=\"canonical\"/>\n<!-- Open Graph / Facebook -->\n<meta content=\"website\" property=\"og:type\"/>\n<meta content=\"https://www.agroverse.shop/event-details-registration/agroverse-cacao-circle-ai-web3-founders-mixer-regenerating-the-amazon-with-tech-visionaries\" property=\"og:url\"/>\n<meta content=\"Join Our Cacao Circle at Orbis86: ETH SF! The Future of Tech: AI x Web3 | Agroverse | Agroverse\" property=\"og:title\"/>\n<meta content=\"Explore the intersection of Web3, AI, and sustainability with us!\" property=\"og:description\"/>\n<meta content=\"https://static.wixstatic.com/media/0e2cde_cd7351ad8ce4476e915158c9b12ec091~mv2.jpg/v1/fill/w_1506,h_1508,al_c,q_90/0e2cde_cd7351ad8ce4476e915158c9b12ec091~mv2.jpg"
      },
      {
        "slug": "cacao-circle-at-create-the-future-summit-2025",
        "title": "Join Our Cacao Circle at Orbis86: ETH SF! The Future of Tech: AI x Web3",
        "status": "past",
        "date": "2025-03-13",
        "date_displayed": "March 13, 2025 at 04:00 PM",
        "time": "04:00 PM",
        "date_source": "page-meta",
        "date_confidence": "low",
        "location": "San Francisco",
        "url": "https://agroverse.shop/event-details-registration/cacao-circle-at-create-the-future-summit-2025/",
        "rsvp_url": null,
        "description": "width=device-width, initial-scale=1.0\" name=\"viewport\"/>\n<meta content=\"IE=edge\" http-equiv=\"X-UA-Compatible\"/>\n<!-- SEO Meta Tags -->\n<title>Join Our Cacao Circle at Orbis86: ETH SF! The Future of Tech: AI x Web3 | Agroverse</title>\n<meta content=\"Explore the intersection of Web3, AI, and sustainability with us!",
        "image": "width=device-width, initial-scale=1.0\" name=\"viewport\"/>\n<meta content=\"IE=edge\" http-equiv=\"X-UA-Compatible\"/>\n<!-- SEO Meta Tags -->\n<title>Join Our Cacao Circle at Orbis86: ETH SF! The Future of Tech: AI x Web3 | Agroverse</title>\n<meta content=\"Explore the intersection of Web3, AI, and sustainability with us!\" name=\"description\"/>\n<link href=\"https://www.agroverse.shop/event-details-registration/cacao-circle-at-create-the-future-summit-2025\" rel=\"canonical\"/>\n<!-- Open Graph / Facebook -->\n<meta content=\"website\" property=\"og:type\"/>\n<meta content=\"https://www.agroverse.shop/event-details-registration/cacao-circle-at-create-the-future-summit-2025\" property=\"og:url\"/>\n<meta content=\"Join Our Cacao Circle at Orbis86: ETH SF! The Future of Tech: AI x Web3 | Agroverse | Agroverse\" property=\"og:title\"/>\n<meta content=\"Explore the intersection of Web3, AI, and sustainability with us!\" property=\"og:description\"/>\n<meta content=\"https://static.wixstatic.com/media/0e2cde_cd7351ad8ce4476e915158c9b12ec091~mv2.jpg/v1/fill/w_1506,h_1508,al_c,q_90/0e2cde_cd7351ad8ce4476e915158c9b12ec091~mv2.jpg"
      },
      {
        "slug": "cacao-circle-at-eth-sf-after-hours-with-crypto-underground-x-stand-with-crypto-cali-tour",
        "title": "Join Our Cacao Circle at Orbis86: ETH SF! The Future of Tech: AI x Web3",
        "status": "past",
        "date": "2025-03-13",
        "date_displayed": "March 13, 2025 at 04:00 PM",
        "time": "04:00 PM",
        "date_source": "page-meta",
        "date_confidence": "low",
        "location": "San Francisco",
        "url": "https://agroverse.shop/event-details-registration/cacao-circle-at-eth-sf-after-hours-with-crypto-underground-x-stand-with-crypto-cali-tour/",
        "rsvp_url": null,
        "description": "width=device-width, initial-scale=1.0\" name=\"viewport\"/>\n<meta content=\"IE=edge\" http-equiv=\"X-UA-Compatible\"/>\n<!-- SEO Meta Tags -->\n<title>Join Our Cacao Circle at Orbis86: ETH SF! The Future of Tech: AI x Web3 | Agroverse</title>\n<meta content=\"Explore the intersection of Web3, AI, and sustainability with us!",
        "image": "width=device-width, initial-scale=1.0\" name=\"viewport\"/>\n<meta content=\"IE=edge\" http-equiv=\"X-UA-Compatible\"/>\n<!-- SEO Meta Tags -->\n<title>Join Our Cacao Circle at Orbis86: ETH SF! The Future of Tech: AI x Web3 | Agroverse</title>\n<meta content=\"Explore the intersection of Web3, AI, and sustainability with us!\" name=\"description\"/>\n<link href=\"https://www.agroverse.shop/event-details-registration/cacao-circle-at-eth-sf-after-hours-with-crypto-underground-x-stand-with-crypto-cali-tour\" rel=\"canonical\"/>\n<!-- Open Graph / Facebook -->\n<meta content=\"website\" property=\"og:type\"/>\n<meta content=\"https://www.agroverse.shop/event-details-registration/cacao-circle-at-eth-sf-after-hours-with-crypto-underground-x-stand-with-crypto-cali-tour\" property=\"og:url\"/>\n<meta content=\"Join Our Cacao Circle at Orbis86: ETH SF! The Future of Tech: AI x Web3 | Agroverse | Agroverse\" property=\"og:title\"/>\n<meta content=\"Explore the intersection of Web3, AI, and sustainability with us!\" property=\"og:description\"/>\n<meta content=\"https://static.wixstatic.com/media/0e2cde_cd7351ad8ce4476e915158c9b12ec091~mv2.jpg/v1/fill/w_1506,h_1508,al_c,q_90/0e2cde_cd7351ad8ce4476e915158c9b12ec091~mv2.jpg"
      },
      {
        "slug": "join-our-cacao-circle-at-orbis86-eth-sf-the-future-of-tech-ai-x-web3",
        "title": "Join Our Cacao Circle at Orbis86: ETH SF! The Future of Tech: AI x Web3",
        "status": "past",
        "date": "2025-03-13",
        "date_displayed": "March 13, 2025 at 04:00 PM",
        "time": "04:00 PM",
        "date_source": "page-meta",
        "date_confidence": "low",
        "location": "San Francisco",
        "url": "https://agroverse.shop/event-details-registration/join-our-cacao-circle-at-orbis86-eth-sf-the-future-of-tech-ai-x-web3/",
        "rsvp_url": null,
        "description": "width=device-width, initial-scale=1.0\" name=\"viewport\"/>\n<meta content=\"IE=edge\" http-equiv=\"X-UA-Compatible\"/>\n<!-- SEO Meta Tags -->\n<title>Join Our Cacao Circle at Orbis86: ETH SF! The Future of Tech: AI x Web3 | Agroverse</title>\n<meta content=\"Explore the intersection of Web3, AI, and sustainability with us!",
        "image": "width=device-width, initial-scale=1.0\" name=\"viewport\"/>\n<meta content=\"IE=edge\" http-equiv=\"X-UA-Compatible\"/>\n<!-- SEO Meta Tags -->\n<title>Join Our Cacao Circle at Orbis86: ETH SF! The Future of Tech: AI x Web3 | Agroverse</title>\n<meta content=\"Explore the intersection of Web3, AI, and sustainability with us!\" name=\"description\"/>\n<link href=\"https://www.agroverse.shop/event-details-registration/join-our-cacao-circle-at-orbis86-eth-sf-the-future-of-tech-ai-x-web3\" rel=\"canonical\"/>\n<!-- Open Graph / Facebook -->\n<meta content=\"website\" property=\"og:type\"/>\n<meta content=\"https://www.agroverse.shop/event-details-registration/join-our-cacao-circle-at-orbis86-eth-sf-the-future-of-tech-ai-x-web3\" property=\"og:url\"/>\n<meta content=\"Join Our Cacao Circle at Orbis86: ETH SF! The Future of Tech: AI x Web3 | Agroverse | Agroverse\" property=\"og:title\"/>\n<meta content=\"Explore the intersection of Web3, AI, and sustainability with us!\" property=\"og:description\"/>\n<meta content=\"https://static.wixstatic.com/media/0e2cde_cd7351ad8ce4476e915158c9b12ec091~mv2.jpg/v1/fill/w_1506,h_1508,al_c,q_90/0e2cde_cd7351ad8ce4476e915158c9b12ec091~mv2.jpg"
      },
      {
        "slug": "under-the-seven-sistars-cacao-circle",
        "title": "Join Our Cacao Circle at Orbis86: ETH SF! The Future of Tech: AI x Web3",
        "status": "past",
        "date": "2025-03-13",
        "date_displayed": "March 13, 2025 at 04:00 PM",
        "time": "04:00 PM",
        "date_source": "page-meta",
        "date_confidence": "low",
        "location": "San Francisco",
        "url": "https://agroverse.shop/event-details-registration/under-the-seven-sistars-cacao-circle/",
        "rsvp_url": null,
        "description": "width=device-width, initial-scale=1.0\" name=\"viewport\"/>\n<meta content=\"IE=edge\" http-equiv=\"X-UA-Compatible\"/>\n<!-- SEO Meta Tags -->\n<title>Join Our Cacao Circle at Orbis86: ETH SF! The Future of Tech: AI x Web3 | Agroverse</title>\n<meta content=\"Explore the intersection of Web3, AI, and sustainability with us!",
        "image": "width=device-width, initial-scale=1.0\" name=\"viewport\"/>\n<meta content=\"IE=edge\" http-equiv=\"X-UA-Compatible\"/>\n<!-- SEO Meta Tags -->\n<title>Join Our Cacao Circle at Orbis86: ETH SF! The Future of Tech: AI x Web3 | Agroverse</title>\n<meta content=\"Explore the intersection of Web3, AI, and sustainability with us!\" name=\"description\"/>\n<link href=\"https://www.agroverse.shop/event-details-registration/under-the-seven-sistars-cacao-circle\" rel=\"canonical\"/>\n<!-- Open Graph / Facebook -->\n<meta content=\"website\" property=\"og:type\"/>\n<meta content=\"https://www.agroverse.shop/event-details-registration/under-the-seven-sistars-cacao-circle\" property=\"og:url\"/>\n<meta content=\"Join Our Cacao Circle at Orbis86: ETH SF! The Future of Tech: AI x Web3 | Agroverse | Agroverse\" property=\"og:title\"/>\n<meta content=\"Explore the intersection of Web3, AI, and sustainability with us!\" property=\"og:description\"/>\n<meta content=\"https://static.wixstatic.com/media/0e2cde_cd7351ad8ce4476e915158c9b12ec091~mv2.jpg/v1/fill/w_1506,h_1508,al_c,q_90/0e2cde_cd7351ad8ce4476e915158c9b12ec091~mv2.jpg"
      },
      {
        "slug": "cacao-circle-at-edge-and-node-hard-crypto-bridging-physical-digital-worlds-co-creator-spotlight",
        "title": "Cacao Circle at Edge and Node: Hard Crypto - Bridging Physical & Digital Worlds + Co-Creator Spotlight",
        "status": "past",
        "date": "2025-02-20",
        "date_displayed": "February 20, 2025 at 06:00 PM",
        "time": "06:00 PM",
        "date_source": "page-meta",
        "date_confidence": "medium",
        "location": "San Francisco",
        "url": "https://agroverse.shop/event-details-registration/cacao-circle-at-edge-and-node-hard-crypto-bridging-physical-digital-worlds-co-creator-spotlight/",
        "rsvp_url": null,
        "description": "width=device-width, initial-scale=1.0\" name=\"viewport\"/>\n<meta content=\"IE=edge\" http-equiv=\"X-UA-Compatible\"/>\n<!-- SEO Meta Tags -->\n<title>Cacao Circle at Edge and Node: Hard Crypto - Bridging Physical & Digital Worlds + Co-Creator Spotlight | Agroverse</title>\n<meta content=\"Dive into the world of Web3 innovation with a transformative cacao circle experience at this House of Web3 event. Connect with visionaries and changemakers while exploring blockchain's potential and fostering mindfulness in a captivating atmosphere.",
        "image": "width=device-width, initial-scale=1.0\" name=\"viewport\"/>\n<meta content=\"IE=edge\" http-equiv=\"X-UA-Compatible\"/>\n<!-- SEO Meta Tags -->\n<title>Cacao Circle at Edge and Node: Hard Crypto - Bridging Physical & Digital Worlds + Co-Creator Spotlight | Agroverse</title>\n<meta content=\"Dive into the world of Web3 innovation with a transformative cacao circle experience at this House of Web3 event. Connect with visionaries and changemakers while exploring blockchain's potential and fostering mindfulness in a captivating atmosphere.\" name=\"description\"/>\n<link href=\"https://www.agroverse.shop/event-details-registration/cacao-circle-at-edge-and-node-hard-crypto-bridging-physical-digital-worlds-co-creator-spotlight\" rel=\"canonical\"/>\n<!-- Open Graph / Facebook -->\n<meta content=\"website\" property=\"og:type\"/>\n<meta content=\"https://www.agroverse.shop/event-details-registration/cacao-circle-at-edge-and-node-hard-crypto-bridging-physical-digital-worlds-co-creator-spotlight\" property=\"og:url\"/>\n<meta content=\"Cacao Circle at Edge and Node: Hard Crypto - Bridging Physical & Digital Worlds + Co-Creator Spotlight | Agroverse | Agroverse\" property=\"og:title\"/>\n<meta content=\"Dive into the world of Web3 innovation with a transformative cacao circle experience at this House of Web3 event. Connect with visionaries and changemakers while exploring blockchain's potential and fostering mindfulness in a captivating atmosphere.\" property=\"og:description\"/>\n<meta content=\"https://static.wixstatic.com/media/0e2cde_31f1d0d2a8074fcc983cbd27020cc856~mv2.jpg/v1/fill/w_2878,h_1506,al_c,q_90/0e2cde_31f1d0d2a8074fcc983cbd27020cc856~mv2.jpg"
      },
      {
        "slug": "agroverse-cacao-circle-regenerating-the-amazon-rainforest-with-the-underdog-founders",
        "title": "Cacao Circle at the Climate Hub - Savoring Sustainability from the Amazon Rainforest",
        "status": "past",
        "date": "2025-01-21",
        "date_displayed": "January 21, 2025 at 07:30 AM",
        "time": "07:30 AM",
        "date_source": "page-meta",
        "date_confidence": "low",
        "location": "Climate Hub",
        "url": "https://agroverse.shop/event-details-registration/agroverse-cacao-circle-regenerating-the-amazon-rainforest-with-the-underdog-founders/",
        "rsvp_url": null,
        "description": "width=device-width, initial-scale=1.0\" name=\"viewport\"/>\n<meta content=\"IE=edge\" http-equiv=\"X-UA-Compatible\"/>\n<!-- SEO Meta Tags -->\n<title>Cacao Circle at the Climate Hub - Savoring Sustainability from the Amazon Rainforest | Agroverse</title>\n<meta content=\"Delight in the flavors of our regenerative Amazonian cacao while connecting with fellow visionaries at the Climate Hub during the World Economic Forum in Davos, Switzerland.",
        "image": "width=device-width, initial-scale=1.0\" name=\"viewport\"/>\n<meta content=\"IE=edge\" http-equiv=\"X-UA-Compatible\"/>\n<!-- SEO Meta Tags -->\n<title>Cacao Circle at the Climate Hub - Savoring Sustainability from the Amazon Rainforest | Agroverse</title>\n<meta content=\"Delight in the flavors of our regenerative Amazonian cacao while connecting with fellow visionaries at the Climate Hub during the World Economic Forum in Davos, Switzerland.\" name=\"description\"/>\n<link href=\"https://www.agroverse.shop/event-details-registration/agroverse-cacao-circle-regenerating-the-amazon-rainforest-with-the-underdog-founders\" rel=\"canonical\"/>\n<!-- Open Graph / Facebook -->\n<meta content=\"website\" property=\"og:type\"/>\n<meta content=\"https://www.agroverse.shop/event-details-registration/agroverse-cacao-circle-regenerating-the-amazon-rainforest-with-the-underdog-founders\" property=\"og:url\"/>\n<meta content=\"Cacao Circle at the Climate Hub - Savoring Sustainability from the Amazon Rainforest | Agroverse | Agroverse\" property=\"og:title\"/>\n<meta content=\"Delight in the flavors of our regenerative Amazonian cacao while connecting with fellow visionaries at the Climate Hub during the World Economic Forum in Davos, Switzerland.\" property=\"og:description\"/>\n<meta content=\"https://static.wixstatic.com/media/0e2cde_fa134f60b3ee4e7a9ff61ed701797626~mv2.jpeg/v1/fill/w_1600,h_1200,al_c,q_85/0e2cde_fa134f60b3ee4e7a9ff61ed701797626~mv2.jpeg"
      },
      {
        "slug": "cacao-circle-at-the-climate-hub-savoring-sustainability-from-the-amazon-rainforest",
        "title": "Cacao Circle at the Climate Hub - Savoring Sustainability from the Amazon Rainforest",
        "status": "past",
        "date": "2025-01-21",
        "date_displayed": "January 21, 2025 at 07:30 AM",
        "time": "07:30 AM",
        "date_source": "page-meta",
        "date_confidence": "low",
        "location": "Climate Hub",
        "url": "https://agroverse.shop/event-details-registration/cacao-circle-at-the-climate-hub-savoring-sustainability-from-the-amazon-rainforest/",
        "rsvp_url": null,
        "description": "width=device-width, initial-scale=1.0\" name=\"viewport\"/>\n<meta content=\"IE=edge\" http-equiv=\"X-UA-Compatible\"/>\n<!-- SEO Meta Tags -->\n<title>Cacao Circle at the Climate Hub - Savoring Sustainability from the Amazon Rainforest | Agroverse</title>\n<meta content=\"Delight in the flavors of our regenerative Amazonian cacao while connecting with fellow visionaries at the Climate Hub during the World Economic Forum in Davos, Switzerland.",
        "image": "width=device-width, initial-scale=1.0\" name=\"viewport\"/>\n<meta content=\"IE=edge\" http-equiv=\"X-UA-Compatible\"/>\n<!-- SEO Meta Tags -->\n<title>Cacao Circle at the Climate Hub - Savoring Sustainability from the Amazon Rainforest | Agroverse</title>\n<meta content=\"Delight in the flavors of our regenerative Amazonian cacao while connecting with fellow visionaries at the Climate Hub during the World Economic Forum in Davos, Switzerland.\" name=\"description\"/>\n<link href=\"https://www.agroverse.shop/event-details-registration/cacao-circle-at-the-climate-hub-savoring-sustainability-from-the-amazon-rainforest\" rel=\"canonical\"/>\n<!-- Open Graph / Facebook -->\n<meta content=\"website\" property=\"og:type\"/>\n<meta content=\"https://www.agroverse.shop/event-details-registration/cacao-circle-at-the-climate-hub-savoring-sustainability-from-the-amazon-rainforest\" property=\"og:url\"/>\n<meta content=\"Cacao Circle at the Climate Hub - Savoring Sustainability from the Amazon Rainforest | Agroverse | Agroverse\" property=\"og:title\"/>\n<meta content=\"Delight in the flavors of our regenerative Amazonian cacao while connecting with fellow visionaries at the Climate Hub during the World Economic Forum in Davos, Switzerland.\" property=\"og:description\"/>\n<meta content=\"https://static.wixstatic.com/media/0e2cde_fa134f60b3ee4e7a9ff61ed701797626~mv2.jpeg/v1/fill/w_1600,h_1200,al_c,q_85/0e2cde_fa134f60b3ee4e7a9ff61ed701797626~mv2.jpeg"
      },
      {
        "slug": "cacao-circle-at-the-social-innovation-hub-uplifting-minds-and-hearts-with-regenerative-cacao",
        "title": "Cacao Circle at the Climate Hub - Savoring Sustainability from the Amazon Rainforest",
        "status": "past",
        "date": "2025-01-21",
        "date_displayed": "January 21, 2025 at 07:30 AM",
        "time": "07:30 AM",
        "date_source": "page-meta",
        "date_confidence": "low",
        "location": "Climate Hub",
        "url": "https://agroverse.shop/event-details-registration/cacao-circle-at-the-social-innovation-hub-uplifting-minds-and-hearts-with-regenerative-cacao/",
        "rsvp_url": null,
        "description": "width=device-width, initial-scale=1.0\" name=\"viewport\"/>\n<meta content=\"IE=edge\" http-equiv=\"X-UA-Compatible\"/>\n<!-- SEO Meta Tags -->\n<title>Cacao Circle at the Climate Hub - Savoring Sustainability from the Amazon Rainforest | Agroverse</title>\n<meta content=\"Delight in the flavors of our regenerative Amazonian cacao while connecting with fellow visionaries at the Climate Hub during the World Economic Forum in Davos, Switzerland.",
        "image": "width=device-width, initial-scale=1.0\" name=\"viewport\"/>\n<meta content=\"IE=edge\" http-equiv=\"X-UA-Compatible\"/>\n<!-- SEO Meta Tags -->\n<title>Cacao Circle at the Climate Hub - Savoring Sustainability from the Amazon Rainforest | Agroverse</title>\n<meta content=\"Delight in the flavors of our regenerative Amazonian cacao while connecting with fellow visionaries at the Climate Hub during the World Economic Forum in Davos, Switzerland.\" name=\"description\"/>\n<link href=\"https://www.agroverse.shop/event-details-registration/cacao-circle-at-the-social-innovation-hub-uplifting-minds-and-hearts-with-regenerative-cacao\" rel=\"canonical\"/>\n<!-- Open Graph / Facebook -->\n<meta content=\"website\" property=\"og:type\"/>\n<meta content=\"https://www.agroverse.shop/event-details-registration/cacao-circle-at-the-social-innovation-hub-uplifting-minds-and-hearts-with-regenerative-cacao\" property=\"og:url\"/>\n<meta content=\"Cacao Circle at the Climate Hub - Savoring Sustainability from the Amazon Rainforest | Agroverse | Agroverse\" property=\"og:title\"/>\n<meta content=\"Delight in the flavors of our regenerative Amazonian cacao while connecting with fellow visionaries at the Climate Hub during the World Economic Forum in Davos, Switzerland.\" property=\"og:description\"/>\n<meta content=\"https://static.wixstatic.com/media/0e2cde_fa134f60b3ee4e7a9ff61ed701797626~mv2.jpeg/v1/fill/w_1600,h_1200,al_c,q_85/0e2cde_fa134f60b3ee4e7a9ff61ed701797626~mv2.jpeg"
      },
      {
        "slug": "cacao-circle-at-okanogan-fall-barter-faire-2025",
        "title": "Cacao Circle at Okanogan Family Faire - Spring Barter Faire 2025",
        "status": "past",
        "date": "2025",
        "date_displayed": "May",
        "time": null,
        "date_source": "slug",
        "date_confidence": "low",
        "location": "Okanogan Family Faire",
        "url": "https://agroverse.shop/event-details-registration/cacao-circle-at-okanogan-fall-barter-faire-2025/",
        "rsvp_url": "https://lu.ma/32vl9dbd",
        "description": "width=device-width, initial-scale=1.0\" name=\"viewport\"/>\n<meta content=\"IE=edge\" http-equiv=\"X-UA-Compatible\"/>\n<!-- SEO Meta Tags -->\n<title>Cacao Circle at Okanogan Family Faire - Spring Barter Faire 2025 | Agroverse</title>\n<meta content=\"Join us for a soulful cacao circle at the Okanogan Family Faire! Taste our cacao tea from Oscar’s Farm 2024 harvest and take home ceremonial cacao from Oscar’s and Sao Jorge’s 2024 harvests.",
        "image": "width=device-width, initial-scale=1.0\" name=\"viewport\"/>\n<meta content=\"IE=edge\" http-equiv=\"X-UA-Compatible\"/>\n<!-- SEO Meta Tags -->\n<title>Cacao Circle at Okanogan Family Faire - Spring Barter Faire 2025 | Agroverse</title>\n<meta content=\"Join us for a soulful cacao circle at the Okanogan Family Faire! Taste our cacao tea from Oscar’s Farm 2024 harvest and take home ceremonial cacao from Oscar’s and Sao Jorge’s 2024 harvests.\" name=\"description\"/>\n<link href=\"https://www.agroverse.shop/event-details-registration/cacao-circle-at-okanogan-fall-barter-faire-2025\" rel=\"canonical\"/>\n<!-- Open Graph / Facebook -->\n<meta content=\"website\" property=\"og:type\"/>\n<meta content=\"https://www.agroverse.shop/event-details-registration/cacao-circle-at-okanogan-fall-barter-faire-2025\" property=\"og:url\"/>\n<meta content=\"Cacao Circle at Okanogan Family Faire - Spring Barter Faire 2025 | Agroverse | Agroverse\" property=\"og:title\"/>\n<meta content=\"Join us for a soulful cacao circle at the Okanogan Family Faire! Taste our cacao tea from Oscar’s Farm 2024 harvest and take home ceremonial cacao from Oscar’s and Sao Jorge’s 2024 harvests.\" property=\"og:description\"/>\n<meta content=\"https://static.wixstatic.com/media/0e2cde_5fba0ffb07f549b18440dcb5519a3a02~mv2.jpg/v1/fill/w_800,h_480,al_c,q_85/0e2cde_5fba0ffb07f549b18440dcb5519a3a02~mv2.jpg"
      },
      {
        "slug": "cacao-circle-at-okanogan-family-faire-spring-barter-faire-2025",
        "title": "Cacao Circle at Okanogan Family Faire - Spring Barter Faire 2025",
        "status": "past",
        "date": "2025",
        "date_displayed": "May",
        "time": null,
        "date_source": "slug",
        "date_confidence": "low",
        "location": "Okanogan Family Faire",
        "url": "https://agroverse.shop/event-details-registration/cacao-circle-at-okanogan-family-faire-spring-barter-faire-2025/",
        "rsvp_url": "https://www.eventbrite.com/e/northwest-nomads-2024-tickets-858149928537",
        "description": "width=device-width, initial-scale=1.0\" name=\"viewport\"/>\n<meta content=\"IE=edge\" http-equiv=\"X-UA-Compatible\"/>\n<!-- SEO Meta Tags -->\n<title>Cacao Circle at Okanogan Family Faire - Spring Barter Faire 2025 | Agroverse</title>\n<meta content=\"Join us for a soulful cacao circle at the Okanogan Family Faire! Taste our cacao tea from Oscar’s Farm 2024 harvest and take home ceremonial cacao from Oscar’s and Sao Jorge’s 2024 harvests.",
        "image": "width=device-width, initial-scale=1.0\" name=\"viewport\"/>\n<meta content=\"IE=edge\" http-equiv=\"X-UA-Compatible\"/>\n<!-- SEO Meta Tags -->\n<title>Cacao Circle at Okanogan Family Faire - Spring Barter Faire 2025 | Agroverse</title>\n<meta content=\"Join us for a soulful cacao circle at the Okanogan Family Faire! Taste our cacao tea from Oscar’s Farm 2024 harvest and take home ceremonial cacao from Oscar’s and Sao Jorge’s 2024 harvests.\" name=\"description\"/>\n<link href=\"https://www.agroverse.shop/event-details-registration/cacao-circle-at-okanogan-family-faire-spring-barter-faire-2025\" rel=\"canonical\"/>\n<!-- Open Graph / Facebook -->\n<meta content=\"website\" property=\"og:type\"/>\n<meta content=\"https://www.agroverse.shop/event-details-registration/cacao-circle-at-okanogan-family-faire-spring-barter-faire-2025\" property=\"og:url\"/>\n<meta content=\"Cacao Circle at Okanogan Family Faire - Spring Barter Faire 2025 | Agroverse | Agroverse\" property=\"og:title\"/>\n<meta content=\"Join us for a soulful cacao circle at the Okanogan Family Faire! Taste our cacao tea from Oscar’s Farm 2024 harvest and take home ceremonial cacao from Oscar’s and Sao Jorge’s 2024 harvests.\" property=\"og:description\"/>\n<meta content=\"https://static.wixstatic.com/media/0e2cde_5fba0ffb07f549b18440dcb5519a3a02~mv2.jpg/v1/fill/w_800,h_480,al_c,q_85/0e2cde_5fba0ffb07f549b18440dcb5519a3a02~mv2.jpg"
      },
      {
        "slug": "web3-holiday-food-drive",
        "title": "Web3 Holiday Food Drive",
        "status": "past",
        "date": "2023-11-05",
        "date_displayed": "November 05, 2023 at 04:00 PM",
        "time": "04:00 PM",
        "date_source": "page-meta",
        "date_confidence": "medium",
        "location": "San Francisco",
        "url": "https://agroverse.shop/event-details-registration/web3-holiday-food-drive/",
        "rsvp_url": null,
        "description": "width=device-width, initial-scale=1.0\" name=\"viewport\"/>\n<meta content=\"IE=edge\" http-equiv=\"X-UA-Compatible\"/>\n<!-- SEO Meta Tags -->\n<title>Web3 Holiday Food Drive | Agroverse</title>\n<meta content=\"A Web3 holiday food drive to support the local food banks will bring together Web3 experts and evangelists. A panel followed by networking, food, and drinks. More info to follow shortly.\n​You will join us and get a taste of our hot chocolate there.",
        "image": "width=device-width, initial-scale=1.0\" name=\"viewport\"/>\n<meta content=\"IE=edge\" http-equiv=\"X-UA-Compatible\"/>\n<!-- SEO Meta Tags -->\n<title>Web3 Holiday Food Drive | Agroverse</title>\n<meta content=\"A Web3 holiday food drive to support the local food banks will bring together Web3 experts and evangelists. A panel followed by networking, food, and drinks. More info to follow shortly.\n​You will join us and get a taste of our hot chocolate there.\" name=\"description\"/>\n<link href=\"https://www.agroverse.shop/event-details-registration/web3-holiday-food-drive\" rel=\"canonical\"/>\n<!-- Open Graph / Facebook -->\n<meta content=\"website\" property=\"og:type\"/>\n<meta content=\"https://www.agroverse.shop/event-details-registration/web3-holiday-food-drive\" property=\"og:url\"/>\n<meta content=\"Web3 Holiday Food Drive | Agroverse | Agroverse\" property=\"og:title\"/>\n<meta content=\"A Web3 holiday food drive to support the local food banks will bring together Web3 experts and evangelists. A panel followed by networking, food, and drinks. More info to follow shortly.\n​You will join us and get a taste of our hot chocolate there.\" property=\"og:description\"/>\n<meta content=\"https://static.wixstatic.com/media/e671cd_579fa76c8d93437e9d2d956de40f285b~mv2.png/v1/fill/w_390,h_397,al_c/e671cd_579fa76c8d93437e9d2d956de40f285b~mv2.png"
      },
      {
        "slug": "halloweekend-free-entrance",
        "title": "HALLOWEEKEND (Free Entrance)",
        "status": "past",
        "date": "2023-10-27",
        "date_displayed": "October 27, 2023 at 07:00 PM",
        "time": "07:00 PM",
        "date_source": "page-meta",
        "date_confidence": "medium",
        "location": "Mountain View",
        "url": "https://agroverse.shop/event-details-registration/halloweekend-free-entrance/",
        "rsvp_url": null,
        "description": "width=device-width, initial-scale=1.0\" name=\"viewport\"/>\n<meta content=\"IE=edge\" http-equiv=\"X-UA-Compatible\"/>\n<!-- SEO Meta Tags -->\n<title>HALLOWEEKEND (Free Entrance) | Agroverse</title>\n<meta content=\"👾 This event hosted by Hacker Dojo is an opportunity to show your nerdy side and celebrate, be on a Costume Contest, win prizes and much more.\n\nYou will taste our fine cocoa drink and benefit your diet by having the opportunity to talk to our collaborators and learn more about the world of cocoa.",
        "image": "width=device-width, initial-scale=1.0\" name=\"viewport\"/>\n<meta content=\"IE=edge\" http-equiv=\"X-UA-Compatible\"/>\n<!-- SEO Meta Tags -->\n<title>HALLOWEEKEND (Free Entrance) | Agroverse</title>\n<meta content=\"👾 This event hosted by Hacker Dojo is an opportunity to show your nerdy side and celebrate, be on a Costume Contest, win prizes and much more.\n\nYou will taste our fine cocoa drink and benefit your diet by having the opportunity to talk to our collaborators and learn more about the world of cocoa.\" name=\"description\"/>\n<link href=\"https://www.agroverse.shop/event-details-registration/halloweekend-free-entrance\" rel=\"canonical\"/>\n<!-- Open Graph / Facebook -->\n<meta content=\"website\" property=\"og:type\"/>\n<meta content=\"https://www.agroverse.shop/event-details-registration/halloweekend-free-entrance\" property=\"og:url\"/>\n<meta content=\"HALLOWEEKEND (Free Entrance) | Agroverse | Agroverse\" property=\"og:title\"/>\n<meta content=\"👾 This event hosted by Hacker Dojo is an opportunity to show your nerdy side and celebrate, be on a Costume Contest, win prizes and much more.\n\nYou will taste our fine cocoa drink and benefit your diet by having the opportunity to talk to our collaborators and learn more about the world of cocoa.\" property=\"og:description\"/>\n<meta content=\"https://static.wixstatic.com/media/e671cd_0b2ea8695081431fbcce8446cd891333~mv2.png/v1/fill/w_988,h_566,al_c/e671cd_0b2ea8695081431fbcce8446cd891333~mv2.png"
      }
    ]
  }
}
